poetry_dev/__init__.py
poetry_dev-0.2.3.dist-info/LICENSE
poetry_dev-0.2.3.dist-info/METADATA
poetry_dev-0.2.3.dist-info/WHEEL
poetry_dev-0.2.3.dist-info/entry_points.txt
poetry_dev-0.2.3.dist-info/RECORD
