Metadata-Version: 2.1
Name: poetry-dev
Version: 0.2.3
Summary: A collection of scripts replace local packages with versions and vice versa
Home-page: https://github.com/mrijken/poetry-dev
License: MIT
Author: Marc Rijken
Author-email: marc@rijken.org
Requires-Python: >=3.6,<4.0
Classifier: License :: OSI Approved :: MIT License
Classifier: Programming Language :: Python :: 3
Classifier: Programming Language :: Python :: 3.6
Classifier: Programming Language :: Python :: 3.7
Classifier: Programming Language :: Python :: 3.8
Classifier: Programming Language :: Python :: 3.9
Classifier: Programming Language :: Python :: 3.10
Classifier: Programming Language :: Python :: 3.11
Classifier: Programming Language :: Python :: 3.12
Requires-Dist: tomlkit (>=0.7.0,<0.8.0)
Requires-Dist: typer (>=0.3.2,<0.4.0)
Project-URL: Repository, https://github.com/mrijken/poetry-dev
